py_package_installer/__init__.py
py_package_installer/installer.py
python_package_installer-1.0.0.5.dist-info/METADATA
python_package_installer-1.0.0.5.dist-info/WHEEL
python_package_installer-1.0.0.5.dist-info/top_level.txt
python_package_installer-1.0.0.5.dist-info/RECORD
